fastai_ulmfit/__init__.py
fastai_ulmfit/_nbdev.py
fastai_ulmfit/embeddings.py
fastai_ulmfit/pretrained.py
fastai_ulmfit-0.0.5.dist-info/LICENSE
fastai_ulmfit-0.0.5.dist-info/METADATA
fastai_ulmfit-0.0.5.dist-info/WHEEL
fastai_ulmfit-0.0.5.dist-info/entry_points.txt
fastai_ulmfit-0.0.5.dist-info/top_level.txt
fastai_ulmfit-0.0.5.dist-info/RECORD
