Metadata-Version: 2.1
Name: fastai-ulmfit
Version: 0.0.5
Summary: Easy to use pretrained-models for fast.ai ULMFiT
Home-page: https://github.com/floleuerer/fastai_ulmfit/tree/main/
Author: Florian Leuerer
Author-email: florian@meansqua.red
License: MIT License
Keywords: fast.ai ulmfit NLP
Platform: UNKNOWN
Classifier: Development Status :: 4 - Beta
Classifier: Intended Audience :: Developers
Classifier: Natural Language :: English
Classifier: Programming Language :: Python :: 3.6
Classifier: Programming Language :: Python :: 3.7
Classifier: Programming Language :: Python :: 3.8
Classifier: License :: OSI Approved :: MIT License
Requires-Python: >=3.6
Requires-Dist: fastai (>=2.2.7)
Requires-Dist: sentencepiece (>=0.1.95)
